Workbook

Sheet About
A1: Horizon Industrial Group - Enterprise AI baseline (DEMO DATA)
A2: Illustrative figures for a fictional organisation, built to demo Executive Presentation Studio
A4: Purpose | B4: Baseline of AI adoption by business line, readiness self-assessment, comparison with a published study, and the USD 15m board request (infrastructure, use-case definition, first implementations).
A5: Organisation | B5: Horizon Industrial Group is fictional. All organisation figures in this workbook are invented for the demo.
A6: Benchmark study | B6: Deloitte AI Institute, State of AI in the Enterprise 2026 - The untapped edge (Jan 2026)
A7: Study method | B7: Survey of 3,235 director- to C-suite leaders in 24 countries, fielded Aug-Sep 2025 (report p.7 and Methodology).
A8: Study PDF | B8: https://www.deloitte.com/content/dam/assets-shared/docs/about/2025/state-of-ai-2026-global.pdf
A9: Colour code | B9: Blue text = input (edit these); black = formula; green = link to another sheet; yellow fill = key assumption.
A10: Sheets | B10: Adoption by Business Line | Readiness | Benchmark vs Study | Use Cases | Investment Request | Targets
A11: Date | B11: Prepared October 2026

Sheet Adoption by Business Line
A1: AI adoption by business line - current state (Q3 2026)
A2: Fictional organisation. Inputs in blue; access, usage and conversion rates are calculated.
A4: Business line | B4: Headcount | C4: Employees with sanctioned AI access | D4: Access rate (% of headcount) | E4: Weekly active AI users | F4: Active use (% of those with access) | G4: Active users (% of headcount) | H4: Use-case ideas logged | I4: Use cases in pilot | J4: Use cases in production | K4: Pilot-to-production rate | L4: AI spend 2026 (USD k) | M4: Data readiness (1-5) | N4: Main barrier reported
A5: Finance | B5: 420 | C5: 95 | D5: =IF(B5=0,0,C5/B5) -> 0.22619048 | E5: 41 | F5: =IF(C5=0,0,E5/C5) -> 0.43157895 | G5: =IF(B5=0,0,E5/B5) -> 0.097619048 | H5: 9 | I5: 3 | J5: 1 | K5: =IF((I5+J5)=0,0,J5/(I5+J5)) -> 0.25 | L5: 180 | M5: 3 | N5: Reconciliation data spread over two ERPs
A6: Human Resources | B6: 260 | C6: 40 | D6: =IF(B6=0,0,C6/B6) -> 0.15384615 | E6: 14 | F6: =IF(C6=0,0,E6/C6) -> 0.35 | G6: =IF(B6=0,0,E6/B6) -> 0.053846154 | H6: 6 | I6: 1 | J6: 0 | K6: =IF((I6+J6)=0,0,J6/(I6+J6)) -> 0 | L6: 60 | M6: 2 | N6: Policy and privacy approval for employee data
A7: Procurement | B7: 310 | C7: 35 | D7: =IF(B7=0,0,C7/B7) -> 0.11290323 | E7: 12 | F7: =IF(C7=0,0,E7/C7) -> 0.34285714 | G7: =IF(B7=0,0,E7/B7) -> 0.038709677 | H7: 7 | I7: 2 | J7: 0 | K7: =IF((I7+J7)=0,0,J7/(I7+J7)) -> 0 | L7: 75 | M7: 2 | N7: Supplier master data incomplete
A8: Supply Chain & Logistics | B8: 1450 | C8: 120 | D8: =IF(B8=0,0,C8/B8) -> 0.082758621 | E8: 38 | F8: =IF(C8=0,0,E8/C8) -> 0.31666667 | G8: =IF(B8=0,0,E8/B8) -> 0.026206897 | H8: 11 | I8: 3 | J8: 1 | K8: =IF((I8+J8)=0,0,J8/(I8+J8)) -> 0.25 | L8: 240 | M8: 2 | N8: No real-time feed from warehouse systems
A9: Operations & Manufacturing | B9: 3200 | C9: 150 | D9: =IF(B9=0,0,C9/B9) -> 0.046875 | E9: 42 | F9: =IF(C9=0,0,E9/C9) -> 0.28 | G9: =IF(B9=0,0,E9/B9) -> 0.013125 | H9: 14 | I9: 4 | J9: 1 | K9: =IF((I9+J9)=0,0,J9/(I9+J9)) -> 0.2 | L9: 310 | M9: 2 | N9: Sensor data not historised; no GPU capacity on site
A10: Sales & Marketing | B10: 680 | C10: 165 | D10: =IF(B10=0,0,C10/B10) -> 0.24264706 | E10: 70 | F10: =IF(C10=0,0,E10/C10) -> 0.42424242 | G10: =IF(B10=0,0,E10/B10) -> 0.10294118 | H10: 10 | I10: 3 | J10: 1 | K10: =IF((I10+J10)=0,0,J10/(I10+J10)) -> 0.25 | L10: 220 | M10: 3 | N10: CRM data quality
A11: Customer Service | B11: 540 | C11: 110 | D11: =IF(B11=0,0,C11/B11) -> 0.2037037 | E11: 52 | F11: =IF(C11=0,0,E11/C11) -> 0.47272727 | G11: =IF(B11=0,0,E11/B11) -> 0.096296296 | H11: 8 | I11: 2 | J11: 1 | K11: =IF((I11+J11)=0,0,J11/(I11+J11)) -> 0.33333333 | L11: 190 | M11: 3 | N11: Knowledge base out of date
A12: Information Technology | B12: 380 | C12: 210 | D12: =IF(B12=0,0,C12/B12) -> 0.55263158 | E12: 118 | F12: =IF(C12=0,0,E12/C12) -> 0.56190476 | G12: =IF(B12=0,0,E12/B12) -> 0.31052632 | H12: 12 | I12: 5 | J12: 2 | K12: =IF((I12+J12)=0,0,J12/(I12+J12)) -> 0.28571429 | L12: 520 | M12: 4 | N12: Shadow AI tools outside policy
A13: Legal & Compliance | B13: 90 | C13: 12 | D13: =IF(B13=0,0,C13/B13) -> 0.13333333 | E13: 4 | F13: =IF(C13=0,0,E13/C13) -> 0.33333333 | G13: =IF(B13=0,0,E13/B13) -> 0.044444444 | H13: 4 | I13: 1 | J13: 0 | K13: =IF((I13+J13)=0,0,J13/(I13+J13)) -> 0 | L13: 30 | M13: 2 | N13: No approved tool for confidential documents
A14: Engineering & R&D | B14: 470 | C14: 95 | D14: =IF(B14=0,0,C14/B14) -> 0.20212766 | E14: 37 | F14: =IF(C14=0,0,E14/C14) -> 0.38947368 | G14: =IF(B14=0,0,E14/B14) -> 0.078723404 | H14: 9 | I14: 2 | J14: 0 | K14: =IF((I14+J14)=0,0,J14/(I14+J14)) -> 0 | L14: 160 | M14: 3 | N14: Drawings and specs not searchable
A15: Total / group | B15: =SUM(B5:B14) -> 7800 | C15: =SUM(C5:C14) -> 1032 | D15: =IF(B15=0,0,C15/B15) -> 0.13230769 | E15: =SUM(E5:E14) -> 428 | F15: =IF(C15=0,0,E15/C15) -> 0.41472868 | G15: =IF(B15=0,0,E15/B15) -> 0.054871795 | H15: =SUM(H5:H14) -> 90 | I15: =SUM(I5:I14) -> 26 | J15: =SUM(J5:J14) -> 7 | K15: =IF((I15+J15)=0,0,J15/(I15+J15)) -> 0.21212121 | L15: =SUM(L5:L14) -> 1985 | M15: =SUMPRODUCT(B5:B14,M5:M14)/B15 -> 2.3679487 | N15: Headcount-weighted readiness
A17: Definitions: 'sanctioned access' = licensed, policy-approved AI tool; 'weekly active' = used at least once a week in Q3 2026.
A18: Pilot-to-production rate = use cases in production / (in pilot + in production). Ideas are not counted.
A19: Data readiness: 1 = data not available or not usable, 3 = usable with manual effort, 5 = governed, real-time, AI-ready.
A20: All figures fictional (demo data).

Sheet Readiness
A1: AI readiness self-assessment vs study
A2: Score 1 (not prepared) to 5 (highly prepared). 'Highly prepared' = score 4 or 5.
A4: Dimension | B4: Our score (1-5) | C4: Our rating | D4: Study: share of organisations 'highly prepared' | E4: Evidence for our score | F4: Study source
A5: Strategy | B5: 3 | C5: =IF(B5>=4,"Highly prepared",IF(B5=3,"Partly prepared","Not prepared")) -> Partly prepared | D5: 0.42 | E5: AI ambition stated in 2026 plan; no funded roadmap or owner per business line. | F5: p.28: 42% highly prepared (up 3 pts)
A6: Risk & governance | B6: 2 | C6: =IF(B6>=4,"Highly prepared",IF(B6=3,"Partly prepared","Not prepared")) -> Not prepared | D6: 0.3 | E6: Acceptable-use policy issued 2025; no model risk process, no agent oversight. | F6: p.28: 30% highly prepared (up 6 pts)
A7: Technical infrastructure | B7: 1 | C7: =IF(B7>=4,"Highly prepared",IF(B7=3,"Partly prepared","Not prepared")) -> Not prepared | D7: 0.43 | E7: No GPU or private AI platform; AI tools run on public SaaS only; integration point-to-point. | F7: p.28: 43% highly prepared (down)
A8: Data management | B8: 2 | C8: =IF(B8>=4,"Highly prepared",IF(B8=3,"Partly prepared","Not prepared")) -> Not prepared | D8: 0.4 | E8: Two ERPs, no enterprise data platform; master data quality issues in 4 of 10 lines. | F8: p.28: 40% highly prepared (down)
A9: Talent | B9: 2 | C9: =IF(B9>=4,"Highly prepared",IF(B9=3,"Partly prepared","Not prepared")) -> Not prepared | D9: 0.2 | E9: 12 data/AI specialists, all in IT; no AI training programme for the business. | F9: p.28: 20% highly prepared (down)
A10: Average score | B10: =AVERAGE(B5:B9) -> 2 | C10: =COUNTIF(C5:C9,"Highly prepared")&" of 5 highly prepared" -> 0 of 5 highly prepared
A12: Scores are a fictional self-assessment. Study figures: Deloitte AI Institute, State of AI in the Enterprise 2026 - The untapped edge (Jan 2026), p.28.

Sheet Benchmark vs Study
A1: Horizon Group vs Deloitte State of AI in the Enterprise 2026
A2: Our figures are linked from the other sheets (green). Study figures are quoted from the report.
A4: Measure | B4: Horizon Group | C4: Study figure | D4: What the study says | E4: Page
A5: Workers with sanctioned access to AI tools | B5: ='Adoption by Business Line'!D15 -> 0.13230769 | C5: 0.6 | D5: Access rose from under 40% to under 60% of workers in one year; leaders (11% of companies) give >80% access. | E5: p.8
A6: Of those with access, share using AI in daily work | B6: ='Adoption by Business Line'!F15 -> 0.41472868 | C6: 0.6 | D6: Fewer than 60% of workers with access use AI in their daily workflow. (Our measure is weekly use.) | E6: p.8
A7: Share of AI pilots moved into production | B7: ='Adoption by Business Line'!K15 -> 0.21212121 | C7: 0.4 | D7: 25% of organisations have moved 40% or more of their AI experiments into production; 54% expect to within 3-6 months. | E7: p.8
A8: Technical infrastructure highly prepared | B8: =Readiness!C7 -> Not prepared | C8: 0.43 | D8: 43% of organisations rate technical infrastructure highly prepared. | E8: p.28
A9: Data management highly prepared | B9: =Readiness!C8 -> Not prepared | C9: 0.4 | D9: 40% rate data management highly prepared. | E9: p.28
A10: Talent highly prepared | B10: =Readiness!C9 -> Not prepared | C10: 0.2 | D10: 20% rate talent highly prepared. | E10: p.28
A11: Risk & governance highly prepared | B11: =Readiness!C6 -> Not prepared | C11: 0.3 | D11: 30% rate risk and governance highly prepared. | E11: p.28
A12: Organisations increasing AI investment | B12: ="USD "&TEXT('Investment Request'!C3,"0.0")&"m proposed" -> USD 15.0m proposed | C12: 0.84 | D12: 84% of organisations are increasing their AI investments. | E12: p.10
A13: Growing revenue through AI today | B13: Not yet | C13: 0.2 | D13: 20% already grow revenue through AI; 74% hope to. | E13: p.10
A15: Source: Deloitte AI Institute, State of AI in the Enterprise 2026 - The untapped edge (Jan 2026), https://www.deloitte.com/content/dam/assets-shared/docs/about/2025/state-of-ai-2026-global.pdf

Sheet Use Cases
A1: Candidate AI use cases - first wave selection
A2: Indicative estimates, to be validated in Workstream B (use-case definition). 'Yes' rows are funded in this request.
A4: # | B4: Use case | C4: Business line | D4: What it does | E4: Indicative annual benefit (USD m) | F4: Implementation cost (USD m) | G4: Complexity | H4: Data readiness (1-5) | I4: Selected for first wave | J4: Simple payback (years)
A5: 1 | B5: Customer service AI assistant | C5: Customer Service | D5: Drafts answers from the knowledge base; summarises cases for agents. | E5: 1.6 | F5: 1.2 | G5: Medium | H5: 3 | I5: Yes | J5: =IF(E5=0,0,F5/E5) -> 0.75
A6: 2 | B6: Invoice and payables automation | C6: Finance | D6: Reads invoices, matches to POs, routes exceptions. | E6: 0.7 | F6: 0.8 | G6: Low | H6: 3 | I6: Yes | J6: =IF(E6=0,0,F6/E6) -> 1.1428571
A7: 3 | B7: Demand forecasting | C7: Supply Chain & Logistics | D7: Weekly SKU-level forecast from orders, seasonality and promotions. | E7: 1.9 | F7: 1.4 | G7: High | H7: 2 | I7: Yes | J7: =IF(E7=0,0,F7/E7) -> 0.73684211
A8: 4 | B8: Predictive maintenance | C8: Operations & Manufacturing | D8: Flags failing equipment from sensor data before breakdown. | E8: 1.8 | F8: 1.1 | G8: High | H8: 2 | I8: Yes | J8: =IF(E8=0,0,F8/E8) -> 0.61111111
A9: 5 | B9: Spend analytics | C9: Procurement | D9: Classifies spend and finds consolidation savings. | E9: 0.6 | F9: 0.5 | G9: Low | H9: 2 | I9: No | J9: =IF(E9=0,0,F9/E9) -> 0.83333333
A10: 6 | B10: Contract review assistant | C10: Legal & Compliance | D10: Highlights non-standard clauses against playbook. | E10: 0.3 | F10: 0.4 | G10: Medium | H10: 2 | I10: No | J10: =IF(E10=0,0,F10/E10) -> 1.3333333
A11: 7 | B11: Proposal and quote drafting | C11: Sales & Marketing | D11: First drafts of proposals from CRM and product data. | E11: 0.5 | F11: 0.4 | G11: Low | H11: 3 | I11: No | J11: =IF(E11=0,0,F11/E11) -> 0.8
A12: 8 | B12: Engineering knowledge search | C12: Engineering & R&D | D12: Searches drawings, specs and past projects in plain language. | E12: 0.4 | F12: 0.6 | G12: Medium | H12: 3 | I12: No | J12: =IF(E12=0,0,F12/E12) -> 1.5
A13: 9 | B13: IT service desk agent | C13: Information Technology | D13: Resolves password, access and how-to tickets end to end. | E13: 0.4 | F13: 0.3 | G13: Low | H13: 4 | I13: No | J13: =IF(E13=0,0,F13/E13) -> 0.75
A14: 10 | B14: HR policy assistant | C14: Human Resources | D14: Answers employee policy questions in English and Arabic. | E14: 0.2 | F14: 0.2 | G14: Low | H14: 2 | I14: No | J14: =IF(E14=0,0,F14/E14) -> 1
B15: Selected (first wave) | E15: =SUMIFS(E5:E14,I5:I14,"Yes") -> 6 | F15: =SUMIFS(F5:F14,I5:I14,"Yes") -> 4.5 | I15: =COUNTIF(I5:I14,"Yes") -> 4
B16: All candidates | E16: =SUM(E5:E14) -> 8.4 | F16: =SUM(F5:F14) -> 6.9
A18: Benefits are fictional, indicative annual run-rate after go-live. Change 'Selected' to Yes/No to re-cut the first wave; the Investment Request sheet updates automatically.

Sheet Investment Request
A1: Board request: USD 15m Enterprise AI programme (2027 - H1 2028)
A3: Total request (USD m) | C3: =C19 -> 15 | D3: Requested envelope | E3: 15 | F3: =IF(ABS(C3-E3)<0.0001,"Within envelope","Differs from envelope") -> Within envelope
A5: Workstream / line item | B5: What it buys | C5: Amount (USD m) | D5: H1 2027 | E5: H2 2027 | F5: H1 2028 | G5: Phasing check | H5: Spend H1 2027 (USD m) | I5: Spend H2 2027 (USD m) | J5: Spend H1 2028 (USD m)
A6: A. Infrastructure upgrade | C6: =SUM(C7:C10) -> 8 | H6: =SUM(H7:H10) -> 3.91 | I6: =SUM(I7:I10) -> 3.11 | J6: =SUM(J7:J10) -> 0.98
A7: Secure AI platform and compute | B7: Private AI platform and GPU capacity for models that cannot run on public SaaS. | C7: 3.5 | D7: 0.6 | E7: 0.4 | F7: 0 | G7: =IF(ABS(SUM(D7:F7)-1)<0.0001,"OK","Check") -> OK | H7: =C7*D7 -> 2.1 | I7: =C7*E7 -> 1.4 | J7: =C7*F7 -> 0
A8: Enterprise data platform and integration | B8: Data platform, pipelines from both ERPs, plant and warehouse systems; master data clean-up. | C8: 2.8 | D8: 0.4 | E8: 0.4 | F8: 0.2 | G8: =IF(ABS(SUM(D8:F8)-1)<0.0001,"OK","Check") -> OK | H8: =C8*D8 -> 1.12 | I8: =C8*E8 -> 1.12 | J8: =C8*F8 -> 0.56
A9: Security, identity and AI governance tooling | B9: Access control, monitoring, model and agent oversight, audit logging. | C9: 0.9 | D9: 0.5 | E9: 0.3 | F9: 0.2 | G9: =IF(ABS(SUM(D9:F9)-1)<0.0001,"OK","Check") -> OK | H9: =C9*D9 -> 0.45 | I9: =C9*E9 -> 0.27 | J9: =C9*F9 -> 0.18
A10: Sanctioned AI tools rollout | B10: Licences and enablement to reach 60% of staff with approved AI tools. | C10: 0.8 | D10: 0.3 | E10: 0.4 | F10: 0.3 | G10: =IF(ABS(SUM(D10:F10)-1)<0.0001,"OK","Check") -> OK | H10: =C10*D10 -> 0.24 | I10: =C10*E10 -> 0.32 | J10: =C10*F10 -> 0.24
A11: B. Use-case identification and definition | C11: =SUM(C12:C14) -> 1.5 | H11: =SUM(H12:H14) -> 0.88 | I11: =SUM(I12:I14) -> 0.47 | J11: =SUM(J12:J14) -> 0.15
A12: Use-case discovery across 10 business lines | B12: Workshops, process mapping, value and feasibility scoring. | C12: 0.6 | D12: 0.8 | E12: 0.2 | F12: 0 | G12: =IF(ABS(SUM(D12:F12)-1)<0.0001,"OK","Check") -> OK | H12: =C12*D12 -> 0.48 | I12: =C12*E12 -> 0.12 | J12: =C12*F12 -> 0
A13: Business cases and prioritisation | B13: Validated business cases for the top 15 use cases; second-wave pipeline. | C13: 0.4 | D13: 0.5 | E13: 0.5 | F13: 0 | G13: =IF(ABS(SUM(D13:F13)-1)<0.0001,"OK","Check") -> OK | H13: =C13*D13 -> 0.2 | I13: =C13*E13 -> 0.2 | J13: =C13*F13 -> 0
A14: AI Centre of Excellence and governance | B14: Core team, policies, training for 1,000 staff, value tracking. | C14: 0.5 | D14: 0.4 | E14: 0.3 | F14: 0.3 | G14: =IF(ABS(SUM(D14:F14)-1)<0.0001,"OK","Check") -> OK | H14: =C14*D14 -> 0.2 | I14: =C14*E14 -> 0.15 | J14: =C14*F14 -> 0.15
A15: C. First implementations | C15: =SUM(C16:C16) -> 4.5 | H15: =SUM(H16:H16) -> 0.9 | I15: =SUM(I16:I16) -> 2.25 | J15: =SUM(J16:J16) -> 1.35
A16: Four priority use cases (see Use Cases sheet) | B16: Customer service assistant, invoice automation, demand forecasting, predictive maintenance. | C16: ='Use Cases'!F15 -> 4.5 | D16: 0.2 | E16: 0.5 | F16: 0.3 | G16: =IF(ABS(SUM(D16:F16)-1)<0.0001,"OK","Check") -> OK | H16: =C16*D16 -> 0.9 | I16: =C16*E16 -> 2.25 | J16: =C16*F16 -> 1.35
A17: D. Contingency | C17: =SUM(C18:C18) -> 1 | H17: =SUM(H18:H18) -> 0 | I17: =SUM(I18:I18) -> 0.5 | J17: =SUM(J18:J18) -> 0.5
A18: Programme contingency | B18: Held centrally; released by the steering committee. | C18: 1 | D18: 0 | E18: 0.5 | F18: 0.5 | G18: =IF(ABS(SUM(D18:F18)-1)<0.0001,"OK","Check") -> OK | H18: =C18*D18 -> 0 | I18: =C18*E18 -> 0.5 | J18: =C18*F18 -> 0.5
A19: Total programme | C19: =SUM(C7,C8,C9,C10,C12,C13,C14,C16,C18) -> 15 | G19: =IF(ABS(H19+I19+J19-C19)<0.0001,"OK","Check") -> OK | H19: =SUM(H7,H8,H9,H10,H12,H13,H14,H16,H18) -> 5.69 | I19: =SUM(I7,I8,I9,I10,I12,I13,I14,I16,I18) -> 6.33 | J19: =SUM(J7,J8,J9,J10,J12,J13,J14,J16,J18) -> 2.98
A21: Value case (first wave)
A22: Indicative annual benefit of first-wave use cases (USD m) | C22: ='Use Cases'!E15 -> 6
A23: Simple payback on the full USD 15m (years) | C23: =IF(C22=0,0,C19/C22) -> 2.5
A24: Share of request on infrastructure | C24: =IF(C19=0,0,C6/C19) -> 0.53333333
A26: All amounts fictional (demo). Phasing percentages per line must total 100% (column G). Payback excludes second-wave use cases enabled by the same infrastructure.

Sheet Targets
A1: Programme targets: today vs end of H1 2028
A2: Current values link to the baseline (green); targets are inputs (blue).
A4: Measure | B4: Today (Q3 2026) | C4: Target (H1 2028) | D4: Change | E4: Why this target
A5: Workers with sanctioned AI access | B5: ='Adoption by Business Line'!D15 -> 0.13230769 | C5: 0.6 | D5: =C5-B5 -> 0.46769231 | E5: Matches the study's current ceiling ('under 60%'), p.8.
A6: Active use among those with access | B6: ='Adoption by Business Line'!F15 -> 0.41472868 | C6: 0.6 | D6: =C6-B6 -> 0.18527132 | E6: Study: fewer than 60% of those with access use AI daily, p.8.
A7: Use cases in production | B7: ='Adoption by Business Line'!J15 -> 7 | C7: 15 | D7: =C7-B7 -> 8 | E7: 7 today + 4 first-wave + 4 second-wave on the new platform.
A8: Pilot-to-production rate | B8: ='Adoption by Business Line'!K15 -> 0.21212121 | C8: 0.4 | D8: =C8-B8 -> 0.18787879 | E8: Reach the 40% level that 25% of organisations in the study have reached, p.8.
A9: Technical infrastructure score (1-5) | B9: =Readiness!B7 -> 1 | C9: 4 | D9: =C9-B9 -> 3 | E9: 'Highly prepared' = 4+; study: 43% of organisations, p.28.
A10: Data management score (1-5) | B10: =Readiness!B8 -> 2 | C10: 4 | D10: =C10-B10 -> 2 | E10: Study: 40% highly prepared, p.28.
A11: Talent score (1-5) | B11: =Readiness!B9 -> 2 | C11: 3 | D11: =C11-B11 -> 1 | E11: Study: only 20% highly prepared; 3 is a realistic step, p.28.
